Metadata-Version: 2.1
Name: cterminal
Version: 1.4.2
Summary: Terminal Tools for python
Home-page: https://github.com/novus-alex/cterminal
Author: Alexandre Hachet
Author-email: alexandrehachet1@gmail.com
License: MIT
Platform: UNKNOWN
Classifier: License :: OSI Approved :: MIT License
Classifier: Programming Language :: Python :: 3
Classifier: Programming Language :: Python :: 3.7
